isolearn/__init__.py
isolearn/generator/__init__.py
isolearn/generator/isolearn_generator.py
isolearn/io/__init__.py
isolearn/io/isolearn_io.py
isolearn/keras/__init__.py
isolearn/keras/isolearn_keras.py
isolearn-0.2.1.dist-info/LICENSE
isolearn-0.2.1.dist-info/METADATA
isolearn-0.2.1.dist-info/WHEEL
isolearn-0.2.1.dist-info/top_level.txt
isolearn-0.2.1.dist-info/RECORD
