Metadata-Version: 2.1
Name: isolearn
Version: 0.2.1
Summary: Keras Genomics Data Generators
Home-page: https://github.com/johli/isolearn
Author: Johannes Linder
Author-email: johannes.linder@hotmail.com
License: UNKNOWN
Platform: UNKNOWN
Classifier: Programming Language :: Python :: 3
Classifier: License :: OSI Approved :: MIT License
Classifier: Operating System :: OS Independent
